app/__init__.py
app/config.py
app/controller.py
app/fields.py
app/models.py
app/routes.py
app/views.py
app/widgets.py
flask_mvc-0.1.5.data/scripts/mvc.py
flask_mvc_app/__init__.py
flask_mvc_app/config.py
flask_mvc_app/controller.py
flask_mvc_app/fields.py
flask_mvc_app/models.py
flask_mvc_app/routes.py
flask_mvc_app/views.py
flask_mvc_app/widgets.py
flask_mvc_app/static/favicon/android-chrome-192x192.png
flask_mvc_app/static/favicon/android-chrome-512x512.png
flask_mvc_app/static/favicon/apple-touch-icon.png
flask_mvc_app/static/favicon/browserconfig.xml
flask_mvc_app/static/favicon/favicon-16x16.png
flask_mvc_app/static/favicon/favicon-32x32.png
flask_mvc_app/static/favicon/favicon.ico
flask_mvc_app/static/favicon/mstile-150x150.png
flask_mvc_app/static/favicon/safari-pinned-tab.svg
flask_mvc_app/static/favicon/site.webmanifest
flask_mvc_app/static/js/bootstrap.min.js
flask_mvc_app/static/js/jquery-3.2.1.slim.min.js
flask_mvc_app/static/js/popper.min.js
flask_mvc_app/static/style/dashboard.css
flask_mvc_app/templates/base.html
flask_mvc_app/templates/create_view.html
flask_mvc_app/templates/delete_view.html
flask_mvc_app/templates/detail_view.html
flask_mvc_app/templates/index.html
flask_mvc_app/templates/list_view.html
flask_mvc_app/templates/namespace_list.html
flask_mvc_app/templates/update_view.html
flask_mvc_app/templates/errors/404.html
flask_mvc_app/templates/errors/500.html
flask_mvc_app/templates/widgets/default.html
flask_mvc_app/templates/widgets/hyperlink.html
flask_mvc_app/templates/widgets/input_checkbox.html
flask_mvc_app/templates/widgets/input_select.html
flask_mvc_app/templates/widgets/input_text.html
flask_mvc_app/templates/widgets/linklist.html
flask_mvc_app/templates/widgets/list.html
flask_mvc-0.1.5.dist-info/LICENSE
flask_mvc-0.1.5.dist-info/METADATA
flask_mvc-0.1.5.dist-info/WHEEL
flask_mvc-0.1.5.dist-info/top_level.txt
flask_mvc-0.1.5.dist-info/RECORD
