Metadata-Version: 2.1
Name: flask-mvc
Version: 0.1.5
Summary: Flask automated MVC experiment
Home-page: https://github.com/alexbredo/flask_mvc_experiment/
Author: Alexander Bredo
Author-email: adagio@live.de
License: UNKNOWN
Platform: UNKNOWN
Classifier: Programming Language :: Python :: 3
Classifier: License :: OSI Approved :: MIT License
Classifier: Operating System :: OS Independent
Requires-Python: >=3
Requires-Dist: flask
Requires-Dist: flask-sqlalchemy
Requires-Dist: flask-migrate
Requires-Dist: sqlalchemy-mixins
